google/cloud/configdelivery/__init__.py
google/cloud/configdelivery/gapic_version.py
google/cloud/configdelivery/py.typed
google/cloud/configdelivery_v1/__init__.py
google/cloud/configdelivery_v1/gapic_metadata.json
google/cloud/configdelivery_v1/gapic_version.py
google/cloud/configdelivery_v1/py.typed
google/cloud/configdelivery_v1/services/__init__.py
google/cloud/configdelivery_v1/services/config_delivery/__init__.py
google/cloud/configdelivery_v1/services/config_delivery/async_client.py
google/cloud/configdelivery_v1/services/config_delivery/client.py
google/cloud/configdelivery_v1/services/config_delivery/pagers.py
google/cloud/configdelivery_v1/services/config_delivery/transports/__init__.py
google/cloud/configdelivery_v1/services/config_delivery/transports/base.py
google/cloud/configdelivery_v1/services/config_delivery/transports/grpc.py
google/cloud/configdelivery_v1/services/config_delivery/transports/grpc_asyncio.py
google/cloud/configdelivery_v1/services/config_delivery/transports/rest.py
google/cloud/configdelivery_v1/services/config_delivery/transports/rest_base.py
google/cloud/configdelivery_v1/types/__init__.py
google/cloud/configdelivery_v1/types/config_delivery.py
google/cloud/configdelivery_v1alpha/__init__.py
google/cloud/configdelivery_v1alpha/gapic_metadata.json
google/cloud/configdelivery_v1alpha/gapic_version.py
google/cloud/configdelivery_v1alpha/py.typed
google/cloud/configdelivery_v1alpha/services/__init__.py
google/cloud/configdelivery_v1alpha/services/config_delivery/__init__.py
google/cloud/configdelivery_v1alpha/services/config_delivery/async_client.py
google/cloud/configdelivery_v1alpha/services/config_delivery/client.py
google/cloud/configdelivery_v1alpha/services/config_delivery/pagers.py
google/cloud/configdelivery_v1alpha/services/config_delivery/transports/__init__.py
google/cloud/configdelivery_v1alpha/services/config_delivery/transports/base.py
google/cloud/configdelivery_v1alpha/services/config_delivery/transports/grpc.py
google_cloud_configdelivery-0.3.0.dist-info/licenses/LICENSE
google_cloud_configdelivery-0.3.0.dist-info/METADATA
google_cloud_configdelivery-0.3.0.dist-info/WHEEL
google_cloud_configdelivery-0.3.0.dist-info/top_level.txt
google_cloud_configdelivery-0.3.0.dist-info/RECORD
